README.md
pyproject.toml
setup.cfg
setup.py
PMCore/__init__.py
PMCore.Client.egg-info/PKG-INFO
PMCore.Client.egg-info/SOURCES.txt
PMCore.Client.egg-info/dependency_links.txt
PMCore.Client.egg-info/requires.txt
PMCore.Client.egg-info/top_level.txt
PMCore/Client/__init__.py
PMCore/Client/api_client.py
PMCore/Client/api_response.py
PMCore/Client/configuration.py
PMCore/Client/exceptions.py
PMCore/Client/py.typed
PMCore/Client/rest.py
PMCore/Client/api/__init__.py
PMCore/Client/api/access_token_api.py
PMCore/Client/api/alipay_api.py
PMCore/Client/api/app_api.py
PMCore/Client/api/app_setting_api.py
PMCore/Client/api/authorize_policy_api.py
PMCore/Client/api/currency_api.py
PMCore/Client/api/ding_talk_api.py
PMCore/Client/api/file_api.py
PMCore/Client/api/o_auth_api.py
PMCore/Client/api/order_api.py
PMCore/Client/api/project_api.py
PMCore/Client/api/service_setting_api.py
PMCore/Client/api/storage_api.py
PMCore/Client/api/system_api.py
PMCore/Client/api/team_api.py
PMCore/Client/api/tenant_api.py
PMCore/Client/api/tenant_file_api.py
PMCore/Client/api/user_api.py
PMCore/Client/api/user_currency_api.py
PMCore/Client/api/user_setting_api.py
PMCore/Client/api/wechat_api.py
PMCore/Client/models/__init__.py
PMCore/Client/models/access_token_post_request.py
PMCore/Client/models/access_token_put_request.py
PMCore/Client/models/alipay_create_order_page_pay_request.py
PMCore/Client/models/alipay_create_order_request.py
PMCore/Client/models/alipay_create_order_wap_pay_request.py
PMCore/Client/models/app.py
PMCore/Client/models/app_setting.py
PMCore/Client/models/app_user_reset_pwd_request.py
PMCore/Client/models/authorize_policy.py
PMCore/Client/models/create_order_request.py
PMCore/Client/models/currency.py
PMCore/Client/models/currency_consume_request.py
PMCore/Client/models/email_sign_in_request.py
PMCore/Client/models/email_sign_up_request.py
PMCore/Client/models/exchange_currency_request.py
PMCore/Client/models/exchange_rate_put_request.py
PMCore/Client/models/execute_function_request.py
PMCore/Client/models/follower_put_model.py
PMCore/Client/models/geo_location_model.py
PMCore/Client/models/grant_request.py
PMCore/Client/models/j_object_api_result.py
